compare_classifiers/__init__.py
compare_classifiers/compare_f1.py
compare_classifiers/confusion_matrices.py
compare_classifiers/ensemble_compare_f1.py
compare_classifiers/ensemble_predict.py
compare_classifiers/error_handling/check_valid_X.py
compare_classifiers/error_handling/check_valid_estimators.py
compare_classifiers/error_handling/check_valid_y.py
compare_classifiers-1.2.0.dist-info/LICENSE
compare_classifiers-1.2.0.dist-info/METADATA
compare_classifiers-1.2.0.dist-info/WHEEL
compare_classifiers-1.2.0.dist-info/RECORD
