Metadata-Version: 2.1
Name: compare_classifiers
Version: 1.2.0
Summary: Comparing metrics such as f1 score and confusion matrix for classifiers and through ensemble stacking or voting and predicting class labels for unseen data by stacking or voting specific classifiers.
License: MIT
Author: Ke Gao, Bryan Lee, Susannah Sun, Wangkai Zhu
Requires-Python: >=3.11,<4.0
Classifier: License :: OSI Approved :: MIT License
Classifier: Programming Language :: Python :: 3
Classifier: Programming Language :: Python :: 3.11
Classifier: Programming Language :: Python :: 3.12
Classifier: Programming Language :: Python :: 3.13
Requires-Dist: matplotlib (>=3.10.0,<4.0.0)
Requires-Dist: pandas (>=2.2.3,<3.0.0)
Requires-Dist: scikit-learn (>=1.6.1,<2.0.0)
